[
  {
    "uniqueid": "66721",
    "show_id": 1738002251,
    "showdate": "2025-06-12",
    "showtitle": "",
    "artist": "Goose",
    "song_id": 714,
    "songname": "Rockdale",
    "artist_id": 1,
    "permalink": "goose-june-12-2025-everwise-amphitheater-at-white-river-state-park-indianapolis-in-usa.html",
    "settype": "Set",
    "setnumber": "1",
    "position": 1,
    "tracktime": "10:05",
    "transition_id": 1,
    "transition": ", ",
    "footnote": "",
    "isjamchart": 0,
    "jamchart_notes": null,
    "venue_id": 443,
    "shownotes": "In Your Eyes was played for the first time since September 14, 2024 (61 shows).",
    "showyear": 2025,
    "showorder": 1,
    "opener": "",
    "tour_id": 40,
    "tourname": "Everything Must Go Summer Tour",
    "soundcheck": "",
    "isverified": 1,
    "slug": "rockdale",
    "isoriginal": 1,
    "original_artist": "Vasudo",
    "venuename": "Everwise Amphitheater at White River State Park",
    "city": "Indianapolis",
    "state": "IN",
    "country": "USA",
    "isreprise": 0,
    "isjam": 0,
    "css_class": "",
    "isrecommended": 0
  },
  {
    "uniqueid": "66723",
    "show_id": 1738002251,
    "showdate": "2025-06-12",
    "showtitle": "",
    "artist": "Goose",
    "song_id": 645,
    "songname": "Hot Love & The Lazy Poet",
    "artist_id": 1,
    "permalink": "goose-june-12-2025-everwise-amphitheater-at-white-river-state-park-indianapolis-in-usa.html",
    "settype": "Set",
    "setnumber": "1",
    "position": 2,
    "tracktime": "5:52",
    "transition_id": 1,
    "transition": ", ",
    "footnote": "",
    "isjamchart": 0,
    "jamchart_notes": null,
    "venue_id": 443,
    "shownotes": "In Your Eyes was played for the first time since September 14, 2024 (61 shows).",
    "showyear": 2025,
    "showorder": 1,
    "opener": "",
    "tour_id": 40,
    "tourname": "Everything Must Go Summer Tour",
    "soundcheck": "",
    "isverified": 1,
    "slug": "hot-love",
    "isoriginal": 1,
    "original_artist": "Vasudo",
    "venuename": "Everwise Amphitheater at White River State Park",
    "city": "Indianapolis",
    "state": "IN",
    "country": "USA",
    "isreprise": 0,
    "isjam": 0,
    "css_class": "",
    "isrecommended": 0
  },
  {
    "uniqueid": "66726",
    "show_id": 1738002251,
    "showdate": "2025-06-12",
    "showtitle": "",
    "artist": "Goose",
    "song_id": 400,
    "songname": "Turned Clouds",
    "artist_id": 1,
    "permalink": "goose-june-12-2025-everwise-amphitheater-at-white-river-state-park-indianapolis-in-usa.html",
    "settype": "Set",
    "setnumber": "1",
    "position": 3,
    "tracktime": "10:48",
    "transition_id": 1,
    "transition": ", ",
    "footnote": "",
    "isjamchart": 0,
    "jamchart_notes": null,
    "venue_id": 443,
    "shownotes": "In Your Eyes was played for the first time since September 14, 2024 (61 shows).",
    "showyear": 2025,
    "showorder": 1,
    "opener": "",
    "tour_id": 40,
    "tourname": "Everything Must Go Summer Tour",
    "soundcheck": "",
    "isverified": 1,
    "slug": "turned-clouds",
    "isoriginal": 1,
    "original_artist": "",
    "venuename": "Everwise Amphitheater at White River State Park",
    "city": "Indianapolis",
    "state": "IN",
    "country": "USA",
    "isreprise": 0,
    "isjam": 0,
    "css_class": "",
    "isrecommended": 0
  },
  {
    "uniqueid": "66730",
    "show_id": 1738002251,
    "showdate": "2025-06-12",
    "showtitle": "",
    "artist": "Goose",
    "song_id": 943,
    "songname": "Draconian Meter Maid",
    "artist_id": 1,
    "permalink": "goose-june-12-2025-everwise-amphitheater-at-white-river-state-park-indianapolis-in-usa.html",
    "settype": "Set",
    "setnumber": "1",
    "position": 4,
    "tracktime": "13:36",
    "transition_id": 1,
    "transition": ", ",
    "footnote": "",
    "isjamchart": 0,
    "jamchart_notes": null,
    "venue_id": 443,
    "shownotes": "In Your Eyes was played for the first time since September 14, 2024 (61 shows).",
    "showyear": 2025,
    "showorder": 1,
    "opener": "",
    "tour_id": 40,
    "tourname": "Everything Must Go Summer Tour",
    "soundcheck": "",
    "isverified": 1,
    "slug": "draconian-meter-ma",
    "isoriginal": 1,
    "original_artist": "Swimmer",
    "venuename": "Everwise Amphitheater at White River State Park",
    "city": "Indianapolis",
    "state": "IN",
    "country": "USA",
    "isreprise": 0,
    "isjam": 0,
    "css_class": "",
    "isrecommended": 0
  },
  {
    "uniqueid": "66735",
    "show_id": 1738002251,
    "showdate": "2025-06-12",
    "showtitle": "",
    "artist": "Goose",
    "song_id": 605,
    "songname": "Earthling or Alien?",
    "artist_id": 1,
    "permalink": "goose-june-12-2025-everwise-amphitheater-at-white-river-state-park-indianapolis-in-usa.html",
    "settype": "Set",
    "setnumber": "1",
    "position": 5,
    "tracktime": "17:08",
    "transition_id": 2,
    "transition": " > ",
    "footnote": "",
    "isjamchart": 0,
    "jamchart_notes": null,
    "venue_id": 443,
    "shownotes": "In Your Eyes was played for the first time since September 14, 2024 (61 shows).",
    "showyear": 2025,
    "showorder": 1,
    "opener": "",
    "tour_id": 40,
    "tourname": "Everything Must Go Summer Tour",
    "soundcheck": "",
    "isverified": 1,
    "slug": "earthling-or-alien",
    "isoriginal": 1,
    "original_artist": "",
    "venuename": "Everwise Amphitheater at White River State Park",
    "city": "Indianapolis",
    "state": "IN",
    "country": "USA",
    "isreprise": 0,
    "isjam": 0,
    "css_class": "",
    "isrecommended": 0
  },
  {
    "uniqueid": "66741",
    "show_id": 1738002251,
    "showdate": "2025-06-12",
    "showtitle": "",
    "artist": "Goose",
    "song_id": 931,
    "songname": "Give It Time",
    "artist_id": 1,
    "permalink": "goose-june-12-2025-everwise-amphitheater-at-white-river-state-park-indianapolis-in-usa.html",
    "settype": "Set",
    "setnumber": "1",
    "position": 6,
    "tracktime": "7:21",
    "transition_id": 1,
    "transition": ", ",
    "footnote": "",
    "isjamchart": 0,
    "jamchart_notes": null,
    "venue_id": 443,
    "shownotes": "In Your Eyes was played for the first time since September 14, 2024 (61 shows).",
    "showyear": 2025,
    "showorder": 1,
    "opener": "",
    "tour_id": 40,
    "tourname": "Everything Must Go Summer Tour",
    "soundcheck": "",
    "isverified": 1,
    "slug": "give-it-time-2",
    "isoriginal": 1,
    "original_artist": "",
    "venuename": "Everwise Amphitheater at White River State Park",
    "city": "Indianapolis",
    "state": "IN",
    "country": "USA",
    "isreprise": 0,
    "isjam": 0,
    "css_class": "",
    "isrecommended": 0
  },
  {
    "uniqueid": "66748",
    "show_id": 1738002251,
    "showdate": "2025-06-12",
    "showtitle": "",
    "artist": "Goose",
    "song_id": 764,
    "songname": "Animal",
    "artist_id": 1,
    "permalink": "goose-june-12-2025-everwise-amphitheater-at-white-river-state-park-indianapolis-in-usa.html",
    "settype": "Set",
    "setnumber": "1",
    "position": 7,
    "tracktime": "17:32",
    "transition_id": 4,
    "transition": "",
    "footnote": "With SALT tease from Rick.",
    "isjamchart": 0,
    "jamchart_notes": null,
    "venue_id": 443,
    "shownotes": "In Your Eyes was played for the first time since September 14, 2024 (61 shows).",
    "showyear": 2025,
    "showorder": 1,
    "opener": "",
    "tour_id": 40,
    "tourname": "Everything Must Go Summer Tour",
    "soundcheck": "",
    "isverified": 1,
    "slug": "animal",
    "isoriginal": 1,
    "original_artist": "",
    "venuename": "Everwise Amphitheater at White River State Park",
    "city": "Indianapolis",
    "state": "IN",
    "country": "USA",
    "isreprise": 0,
    "isjam": 0,
    "css_class": "",
    "isrecommended": 0
  },
  {
    "uniqueid": "66770",
    "show_id": 1738002251,
    "showdate": "2025-06-12",
    "showtitle": "",
    "artist": "Goose",
    "song_id": 723,
    "songname": "Pancakes",
    "artist_id": 1,
    "permalink": "goose-june-12-2025-everwise-amphitheater-at-white-river-state-park-indianapolis-in-usa.html",
    "settype": "Set",
    "setnumber": "2",
    "position": 8,
    "tracktime": "20:59",
    "transition_id": 1,
    "transition": ", ",
    "footnote": "Unfinished.",
    "isjamchart": 0,
    "jamchart_notes": null,
    "venue_id": 443,
    "shownotes": "In Your Eyes was played for the first time since September 14, 2024 (61 shows).",
    "showyear": 2025,
    "showorder": 1,
    "opener": "",
    "tour_id": 40,
    "tourname": "Everything Must Go Summer Tour",
    "soundcheck": "",
    "isverified": 1,
    "slug": "pancakes",
    "isoriginal": 1,
    "original_artist": "Great Blue",
    "venuename": "Everwise Amphitheater at White River State Park",
    "city": "Indianapolis",
    "state": "IN",
    "country": "USA",
    "isreprise": 0,
    "isjam": 0,
    "css_class": "",
    "isrecommended": 0
  },
  {
    "uniqueid": "66779",
    "show_id": 1738002251,
    "showdate": "2025-06-12",
    "showtitle": "",
    "artist": "Goose",
    "song_id": 498,
    "songname": "In Your Eyes",
    "artist_id": 1,
    "permalink": "goose-june-12-2025-everwise-amphitheater-at-white-river-state-park-indianapolis-in-usa.html",
    "settype": "Set",
    "setnumber": "2",
    "position": 9,
    "tracktime": "17:50",
    "transition_id": 2,
    "transition": " > ",
    "footnote": "Peter Gabriel.",
    "isjamchart": 0,
    "jamchart_notes": null,
    "venue_id": 443,
    "shownotes": "In Your Eyes was played for the first time since September 14, 2024 (61 shows).",
    "showyear": 2025,
    "showorder": 1,
    "opener": "",
    "tour_id": 40,
    "tourname": "Everything Must Go Summer Tour",
    "soundcheck": "",
    "isverified": 1,
    "slug": "in-your-eyes",
    "isoriginal": 0,
    "original_artist": "Peter Gabriel",
    "venuename": "Everwise Amphitheater at White River State Park",
    "city": "Indianapolis",
    "state": "IN",
    "country": "USA",
    "isreprise": 0,
    "isjam": 0,
    "css_class": null,
    "isrecommended": 0
  },
  {
    "uniqueid": "66789",
    "show_id": 1738002251,
    "showdate": "2025-06-12",
    "showtitle": "",
    "artist": "Goose",
    "song_id": 933,
    "songname": "How It Ends",
    "artist_id": 1,
    "permalink": "goose-june-12-2025-everwise-amphitheater-at-white-river-state-park-indianapolis-in-usa.html",
    "settype": "Set",
    "setnumber": "2",
    "position": 10,
    "tracktime": "11:59",
    "transition_id": 1,
    "transition": ", ",
    "footnote": "",
    "isjamchart": 0,
    "jamchart_notes": null,
    "venue_id": 443,
    "shownotes": "In Your Eyes was played for the first time since September 14, 2024 (61 shows).",
    "showyear": 2025,
    "showorder": 1,
    "opener": "",
    "tour_id": 40,
    "tourname": "Everything Must Go Summer Tour",
    "soundcheck": "",
    "isverified": 1,
    "slug": "how-it-ends-2",
    "isoriginal": 1,
    "original_artist": "Vasudo",
    "venuename": "Everwise Amphitheater at White River State Park",
    "city": "Indianapolis",
    "state": "IN",
    "country": "USA",
    "isreprise": 0,
    "isjam": 0,
    "css_class": "",
    "isrecommended": 0
  },
  {
    "uniqueid": "66800",
    "show_id": 1738002251,
    "showdate": "2025-06-12",
    "showtitle": "",
    "artist": "Goose",
    "song_id": 418,
    "songname": "Tumble",
    "artist_id": 1,
    "permalink": "goose-june-12-2025-everwise-amphitheater-at-white-river-state-park-indianapolis-in-usa.html",
    "settype": "Set",
    "setnumber": "2",
    "position": 11,
    "tracktime": "15:56",
    "transition_id": 5,
    "transition": "",
    "footnote": "",
    "isjamchart": 1,
    "jamchart_notes": "Pure balls-to-the-walls Goontz. ",
    "venue_id": 443,
    "shownotes": "In Your Eyes was played for the first time since September 14, 2024 (61 shows).",
    "showyear": 2025,
    "showorder": 1,
    "opener": "",
    "tour_id": 40,
    "tourname": "Everything Must Go Summer Tour",
    "soundcheck": "",
    "isverified": 1,
    "slug": "tumble",
    "isoriginal": 1,
    "original_artist": "Vasudo",
    "venuename": "Everwise Amphitheater at White River State Park",
    "city": "Indianapolis",
    "state": "IN",
    "country": "USA",
    "isreprise": 0,
    "isjam": 0,
    "css_class": "",
    "isrecommended": 0
  },
  {
    "uniqueid": "66823",
    "show_id": 1738002251,
    "showdate": "2025-06-12",
    "showtitle": "",
    "artist": "Goose",
    "song_id": 403,
    "songname": "Arcadia",
    "artist_id": 1,
    "permalink": "goose-june-12-2025-everwise-amphitheater-at-white-river-state-park-indianapolis-in-usa.html",
    "settype": "Set",
    "setnumber": "e",
    "position": 12,
    "tracktime": "7:01",
    "transition_id": 5,
    "transition": "",
    "footnote": "",
    "isjamchart": 0,
    "jamchart_notes": null,
    "venue_id": 443,
    "shownotes": "In Your Eyes was played for the first time since September 14, 2024 (61 shows).",
    "showyear": 2025,
    "showorder": 1,
    "opener": "",
    "tour_id": 40,
    "tourname": "Everything Must Go Summer Tour",
    "soundcheck": "",
    "isverified": 1,
    "slug": "arcadia",
    "isoriginal": 1,
    "original_artist": "",
    "venuename": "Everwise Amphitheater at White River State Park",
    "city": "Indianapolis",
    "state": "IN",
    "country": "USA",
    "isreprise": 0,
    "isjam": 0,
    "css_class": "",
    "isrecommended": 0
  }
]